proxynt/__init__.py
proxynt/run_client.py
proxynt/run_server.py
proxynt/test_exchange.py
proxynt/client/__init__.py
proxynt/client/abstract_tunnel.py
proxynt/client/clear_nonce_task.py
proxynt/client/heart_beat_task.py
proxynt/client/kcp_tunnel_impl.py
proxynt/client/n4_tunnel_manager.py
proxynt/client/quic_tunnel_impl.py
proxynt/client/tcp_forward_client.py
proxynt/client/tunnel_protocol.py
proxynt/client/udp_forward_client.py
proxynt/common/__init__.py
proxynt/common/cert_utils.py
proxynt/common/encrypt_utils.py
proxynt/common/kcp.py
proxynt/common/logger_factory.py
proxynt/common/n4_protocol.py
proxynt/common/n4_punch.py
proxynt/common/nat_serialization.py
proxynt/common/nat_serialization_v1.py
proxynt/common/nat_serialization_v2.py
proxynt/common/pool.py
proxynt/common/register_append_data.py
proxynt/common/speed_limit.py
proxynt/common/crypto/__init__.py
proxynt/common/crypto/table.py
proxynt/common/websocket/__init__.py
proxynt/common/websocket/_abnf.py
proxynt/common/websocket/_app.py
proxynt/common/websocket/_cookiejar.py
proxynt/common/websocket/_core.py
proxynt/common/websocket/_exceptions.py
proxynt/common/websocket/_handshake.py
proxynt/common/websocket/_http.py
proxynt/common/websocket/_logging.py
proxynt/common/websocket/_socket.py
proxynt/common/websocket/_ssl_compat.py
proxynt/common/websocket/_url.py
proxynt/common/websocket/_utils.py
proxynt/common/websocket/_wsdump.py
proxynt/common/websocket/tests/__init__.py
proxynt/common/websocket/tests/echo-server.py
proxynt/common/websocket/tests/test_abnf.py
proxynt/common/websocket/tests/test_app.py
proxynt/common/websocket/tests/test_cookiejar.py
proxynt/common/websocket/tests/test_http.py
proxynt/common/websocket/tests/test_url.py
proxynt/common/websocket/tests/test_websocket.py
proxynt/constant/__init__.py
proxynt/constant/message_type_constnat.py
proxynt/constant/system_constant.py
proxynt/context/__init__.py
proxynt/context/context_utils.py
proxynt/entity/__init__.py
proxynt-2.0.45.dist-info/LICENSE
proxynt-2.0.45.dist-info/METADATA
proxynt-2.0.45.dist-info/WHEEL
proxynt-2.0.45.dist-info/entry_points.txt
proxynt-2.0.45.dist-info/top_level.txt
proxynt-2.0.45.dist-info/RECORD
