Metadata-Version: 2.1
Name: proxynt
Version: 2.0.45
Summary: UNKNOWN
Home-page: https://github.com/sazima/proxynt
License: UNKNOWN
Platform: UNKNOWN
License-File: LICENSE
Requires-Dist: tornado
Requires-Dist: typing-extensions
Requires-Dist: xxhash (>=3.0.0)
Requires-Dist: msgpack
Requires-Dist: uvloop (<0.15) ; sys_platform != "win32" and python_version < "3.7"
Requires-Dist: uvloop (==0.22.0) ; sys_platform != "win32" and python_version >= "3.7"
Requires-Dist: winloop (>=0.1.0) ; sys_platform == "win32"
Provides-Extra: snappy
Requires-Dist: python-snappy ; extra == 'snappy'
